cached_task
tests
