Metadata-Version: 1.0
Name: cached-task
Version: 2021.4.5
Summary: cached_task
Home-page: UNKNOWN
Author: Bogdan Mustiata
Author-email: bogdan.mustiata@gmail.com
License: BSD
Platform: UNKNOWN
